Metadata-Version: 1.0
Name: madaxx-exer
Version: 0.1
Summary: Gaussian distributions
Home-page: UNKNOWN
Author: Madaki Fatsen
Author-email: madakifatsen@gmail.com
License: UNKNOWN
Platform: UNKNOWN
